zettelgeist/__init__.py
zettelgeist/zcreate.py
zettelgeist/zdb.py
zettelgeist/zettel.py
zettelgeist/zfind.py
zettelgeist/zimport.py
zettelgeist/zquery.py
zettelgeist/zutils.py
zettelgeist/zversion.py
zettelgeist-1.1.5.dist-info/LICENSE
zettelgeist-1.1.5.dist-info/METADATA
zettelgeist-1.1.5.dist-info/WHEEL
zettelgeist-1.1.5.dist-info/entry_points.txt
zettelgeist-1.1.5.dist-info/top_level.txt
zettelgeist-1.1.5.dist-info/RECORD
