Metadata-Version: 2.1
Name: zettelgeist
Version: 1.1.5
Summary: ZettelGeist - a historiographically focused notetaking system
Home-page: https://github.com/zettelgeist/zettelgeist
Author: ZettelGeist Laboratories
Author-email: gkt@cs.luc.edu
License: Apache License 2.0
Keywords: notetaking,YAML,Markdown,sqlite3,GitHub
Classifier: Development Status :: 4 - Beta
Classifier: Programming Language :: Python :: 3
Classifier: Programming Language :: Python :: 3.10
Classifier: Programming Language :: Python :: 3 :: Only
Classifier: Topic :: Software Development
Classifier: License :: OSI Approved :: Apache Software License
Requires-Python: >=3.10
License-File: LICENSE
Requires-Dist: python-frontmatter
Requires-Dist: tatsu
